tenpy/__init__.py
tenpy/__main__.py
tenpy/version.py
tenpy/algorithms/__init__.py
tenpy/algorithms/algorithm.py
tenpy/algorithms/disentangler.py
tenpy/algorithms/dmrg.py
tenpy/algorithms/dmrg_parallel.py
tenpy/algorithms/exact_diag.py
tenpy/algorithms/mpo_evolution.py
tenpy/algorithms/mps_common.py
tenpy/algorithms/network_contractor.py
tenpy/algorithms/plane_wave_excitation.py
tenpy/algorithms/purification.py
tenpy/algorithms/tdvp.py
tenpy/algorithms/tebd.py
tenpy/algorithms/truncation.py
tenpy/algorithms/vumps.py
tenpy/linalg/__init__.py
tenpy/linalg/_npc_helper.cpp
tenpy/linalg/_npc_helper.cpython-314-x86_64-linux-gnu.so
tenpy/linalg/_npc_helper.pyx
tenpy/linalg/charges.py
tenpy/linalg/krylov_based.py
tenpy/linalg/np_conserved.py
tenpy/linalg/random_matrix.py
tenpy/linalg/sparse.py
tenpy/linalg/svd_robust.py
tenpy/linalg/truncation.py
tenpy/models/__init__.py
tenpy/models/aklt.py
tenpy/models/clock.py
tenpy/models/fermions_spinless.py
tenpy/models/haldane.py
tenpy/models/hofstadter.py
tenpy/models/hubbard.py
tenpy/models/lattice.py
tenpy/models/mixed_xk.py
tenpy/models/model.py
tenpy/models/molecular.py
tenpy/models/pxp.py
tenpy/models/spins.py
tenpy/models/spins_nnn.py
tenpy/models/tf_ising.py
tenpy/models/tj_model.py
tenpy/models/toric_code.py
tenpy/models/xxz_chain.py
tenpy/networks/__init__.py
tenpy/networks/momentum_mps.py
tenpy/networks/mpo.py
tenpy/networks/mps.py
tenpy/networks/purification_mps.py
tenpy/networks/site.py
tenpy/networks/terms.py
tenpy/networks/uniform_mps.py
tenpy/simulations/__init__.py
tenpy/simulations/ground_state_search.py
tenpy/simulations/measurement.py
tenpy/simulations/post_processing.py
tenpy/simulations/simulation.py
tenpy/simulations/time_evolution.py
tenpy/tools/__init__.py
tenpy/tools/cache.py
tenpy/tools/docs.py
tenpy/tools/events.py
tenpy/tools/fit.py
tenpy/tools/hdf5_io.py
tenpy/tools/math.py
tenpy/tools/misc.py
tenpy/tools/optimization.py
physics_tenpy-1.1.0.dist-info/METADATA
physics_tenpy-1.1.0.dist-info/WHEEL
physics_tenpy-1.1.0.dist-info/entry_points.txt
physics_tenpy-1.1.0.dist-info/top_level.txt
physics_tenpy-1.1.0.dist-info/RECORD
physics_tenpy-1.1.0.dist-info/licenses/LICENSE
