Metadata-Version: 2.4
Name: physics-tenpy
Version: 1.1.0
Summary: Simulation of quantum many-body systems with tensor networks in Python
Author: TeNPy Developer Team
Maintainer-email: Johannes Hauschild <tenpy@johannes-hauschild.de>, Jakob Unfried <jakob.unfried@tum.de>
License-Expression: Apache-2.0
Project-URL: Homepage, https://github.com/tenpy/tenpy
Project-URL: Documentation, https://tenpy.readthedocs.io/
Project-URL: Source, https://github.com/tenpy/tenpy
Project-URL: User Forum, https://tenpy.johannes-hauschild.de
Project-URL: Bug Tracker, https://github.com/tenpy/tenpy/issues
Keywords: tensor networks,matrix product states
Classifier: Development Status :: 5 - Production/Stable
Classifier: Intended Audience :: Science/Research
Classifier: Intended Audience :: Developers
Classifier: Natural Language :: English
Classifier: Programming Language :: C
Classifier: Programming Language :: Python
Classifier: Programming Language :: Python :: 3
Classifier: Programming Language :: Python :: 3.10
Classifier: Programming Language :: Python :: 3.11
Classifier: Programming Language :: Python :: 3.12
Classifier: Programming Language :: Python :: 3.13
Classifier: Programming Language :: Python :: 3.14
Classifier: Operating System :: Unix
Classifier: Operating System :: MacOS
Classifier: Operating System :: Microsoft :: Windows
Classifier: Topic :: Scientific/Engineering
Classifier: Topic :: Scientific/Engineering :: Physics
Requires-Python: >=3.10
License-File: LICENSE
Requires-Dist: numpy
Requires-Dist: scipy
Provides-Extra: plot
Requires-Dist: matplotlib; extra == "plot"
Provides-Extra: io
Requires-Dist: h5py; extra == "io"
Requires-Dist: pyyaml; extra == "io"
Provides-Extra: memory
Requires-Dist: psutil; extra == "memory"
Provides-Extra: extra
Requires-Dist: bottleneck; extra == "extra"
Provides-Extra: docbuild
Requires-Dist: Sphinx; extra == "docbuild"
Requires-Dist: sphinx-rtd-theme; extra == "docbuild"
Requires-Dist: sphinxcontrib-bibtex; extra == "docbuild"
Requires-Dist: matplotlib; extra == "docbuild"
Requires-Dist: ipykernel; extra == "docbuild"
Requires-Dist: nbsphinx; extra == "docbuild"
Requires-Dist: pandoc; extra == "docbuild"
Requires-Dist: sphinx_copybutton; extra == "docbuild"
Provides-Extra: test
Requires-Dist: pytest>=6.0; extra == "test"
Requires-Dist: physics_tenpy[io,memory]; extra == "test"
Provides-Extra: lint
Requires-Dist: ruff; extra == "lint"
Requires-Dist: pre-commit; extra == "lint"
Requires-Dist: flake8; extra == "lint"
Requires-Dist: flake8-rst-docstrings; extra == "lint"
Provides-Extra: all
Requires-Dist: physics_tenpy[docbuild,extra,io,lint,plot,test]; extra == "all"
Dynamic: license-file
